dagster_anthropic/__init__.py
dagster_anthropic/resource.py
dagster_anthropic-0.0.5.dist-info/METADATA
dagster_anthropic-0.0.5.dist-info/WHEEL
dagster_anthropic-0.0.5.dist-info/top_level.txt
dagster_anthropic-0.0.5.dist-info/RECORD
