Metadata-Version: 2.4
Name: dagster-anthropic
Version: 0.0.5
Summary: Dagster integration with Anthropic
Requires-Python: >=3.10
Requires-Dist: dagster>=1.8.0
Requires-Dist: anthropic>=0.42.0
